NetkillerDeveloperFix1/README.md
NetkillerDeveloperFix1/__init__.py
NetkillerDeveloperFix1/__main__.py
NetkillerDeveloperFix1/file.epub
NetkillerDeveloperFix1/index.html
NetkillerDeveloperFix1/css/__init__.py
NetkillerDeveloperFix1/css/annotations.css
NetkillerDeveloperFix1/css/main.css
NetkillerDeveloperFix1/css/normalize.css
NetkillerDeveloperFix1/css/popup.css
NetkillerDeveloperFix1/font/__init__.py
NetkillerDeveloperFix1/font/fontello.eot
NetkillerDeveloperFix1/font/fontello.svg
NetkillerDeveloperFix1/font/fontello.ttf
NetkillerDeveloperFix1/font/fontello.woff
NetkillerDeveloperFix1/img/__init__.py
NetkillerDeveloperFix1/img/annotator-glyph-sprite.png
NetkillerDeveloperFix1/img/annotator-icon-sprite.png
NetkillerDeveloperFix1/img/apple-touch-icon.png
NetkillerDeveloperFix1/img/cancelfullscreen.png
NetkillerDeveloperFix1/img/close.png
NetkillerDeveloperFix1/img/fullscreen.png
NetkillerDeveloperFix1/img/loader.gif
NetkillerDeveloperFix1/img/menu-icon.png
NetkillerDeveloperFix1/img/save.png
NetkillerDeveloperFix1/img/saved.png
NetkillerDeveloperFix1/img/settings-s.png
NetkillerDeveloperFix1/img/settings.png
NetkillerDeveloperFix1/img/star.png
NetkillerDeveloperFix1/js/__init__.py
NetkillerDeveloperFix1/js/epub.js
NetkillerDeveloperFix1/js/epub.min.js
NetkillerDeveloperFix1/js/epub.min.map
NetkillerDeveloperFix1/js/hooks.min.js
NetkillerDeveloperFix1/js/hooks.min.map
NetkillerDeveloperFix1/js/reader.js
NetkillerDeveloperFix1/js/reader.js.map
NetkillerDeveloperFix1/js/reader.min.js
NetkillerDeveloperFix1/js/reader.min.map
NetkillerDeveloperFix1/js/hooks/__init__.py
NetkillerDeveloperFix1/js/hooks/extensions/__init__.py
NetkillerDeveloperFix1/js/hooks/extensions/highlight.js
NetkillerDeveloperFix1/js/libs/__init__.py
NetkillerDeveloperFix1/js/libs/jquery.min.js
NetkillerDeveloperFix1/js/libs/localforage.min.js
NetkillerDeveloperFix1/js/libs/screenfull.js
NetkillerDeveloperFix1/js/libs/screenfull.min.js
NetkillerDeveloperFix1/js/libs/zip.min.js
netkiller_developer_fix1-2025.3.24.1.dist-info/METADATA
netkiller_developer_fix1-2025.3.24.1.dist-info/WHEEL
netkiller_developer_fix1-2025.3.24.1.dist-info/entry_points.txt
netkiller_developer_fix1-2025.3.24.1.dist-info/top_level.txt
netkiller_developer_fix1-2025.3.24.1.dist-info/RECORD
